btx_lib_mail/__init__.py
btx_lib_mail/__init__conf__.py
btx_lib_mail/__main__.py
btx_lib_mail/behaviors.py
btx_lib_mail/cli.py
btx_lib_mail/lib_mail.py
btx_lib_mail/py.typed
btx_lib_mail-1.3.0.dist-info/METADATA
btx_lib_mail-1.3.0.dist-info/WHEEL
btx_lib_mail-1.3.0.dist-info/entry_points.txt
btx_lib_mail-1.3.0.dist-info/licenses/LICENSE
btx_lib_mail-1.3.0.dist-info/RECORD
